pdfextract/__init__.py
pdfextract/data/PDFExtract.jar
pdfextract/data/PDFExtract.json
pdfextract/extract/__init__.py
python_pdfextract-3.1.2.dist-info/LICENSE.txt
python_pdfextract-3.1.2.dist-info/METADATA
python_pdfextract-3.1.2.dist-info/WHEEL
python_pdfextract-3.1.2.dist-info/top_level.txt
python_pdfextract-3.1.2.dist-info/RECORD
